// Code generated by POJ 0.1
public class var_declarations {
	public static main([java/lang/String)V {
		ldc "Message 1!"
		astore 1
		ldc "Message 2!"
		astore 2
		ldc "Message 3!"
		astore 3
		ldc "Message 4!"
		astore 4
		getstatic java/lang/System.out java/io/PrintStream
		aload 1
		invokevirtual java/io/PrintStream.print(java/lang/String)V
		getstatic java/lang/System.out java/io/PrintStream
		invokevirtual java/io/PrintStream.println()V
		getstatic java/lang/System.out java/io/PrintStream
		aload 2
		invokevirtual java/io/PrintStream.print(java/lang/String)V
		getstatic java/lang/System.out java/io/PrintStream
		invokevirtual java/io/PrintStream.println()V
		getstatic java/lang/System.out java/io/PrintStream
		aload 3
		invokevirtual java/io/PrintStream.print(java/lang/String)V
		getstatic java/lang/System.out java/io/PrintStream
		invokevirtual java/io/PrintStream.println()V
		getstatic java/lang/System.out java/io/PrintStream
		aload 4
		invokevirtual java/io/PrintStream.print(java/lang/String)V
		getstatic java/lang/System.out java/io/PrintStream
		invokevirtual java/io/PrintStream.println()V
		return
	}
}
