// Code generated by POJ 0.1
public class fatorial_fixed_number {
	public static numero I
	static fatorial(I)I {
		iload 0
		sipush 0
		if_icmpge L4
		iconst 1
		goto L5
		L4:
		iconst 0
		L5:
		ifeq L1
		sipush 0
		istore 100
		goto L2
		L1:
		iload 0
		sipush 1
		if_icmpgt L9
		iconst 1
		goto L10
		L9:
		iconst 0
		L10:
		ifeq L6
		sipush 1
		istore 100
		goto L7
		L6:
		iload 0
		iload 0
		sipush 1
		isub 
		invokestatic fatorial_fixed_number.fatorial(I)I 
		imul 
		istore 100
		L7:
		L2:
		iload 100
		ireturn 
	}
	public static main([java/lang/String)V {
		sipush 5
		putstatic fatorial_fixed_number.numero I
		getstatic java/lang/System.out java/io/PrintStream
		ldc "O fatorial de "
		invokevirtual java/io/PrintStream.print(java/lang/String)V
		getstatic java/lang/System.out java/io/PrintStream
		getstatic fatorial_fixed_number.numero I
		invokevirtual java/io/PrintStream.print(I)V
		getstatic java/lang/System.out java/io/PrintStream
		ldc " e: "
		invokevirtual java/io/PrintStream.print(java/lang/String)V
		getstatic java/lang/System.out java/io/PrintStream
		getstatic fatorial_fixed_number.numero I
		invokestatic fatorial_fixed_number.fatorial(I)I 
		invokevirtual java/io/PrintStream.print(I)V
		getstatic java/lang/System.out java/io/PrintStream
		invokevirtual java/io/PrintStream.println()V
		return
	}
}
