// Code generated by POJ 0.1
public class global_and_local_vars_4 {
	public static myglobal1 I
	public static myglobal2 I
	public static myglobal3 I
	public static addedValue I
	static addvalues(I, I)I {
		iload 0
		iload 1
		iadd
		istore 2
		iload 2
		getstatic global_and_local_vars_4.addedValue I
		iadd
		istore 3
		iload 3
		istore 100
		iload 100
		ireturn
	}
	static mulvalues(I, I)I {
		iload 0
		iload 1
		imul
		istore 2
		iload 2
		getstatic global_and_local_vars_4.addedValue I
		iadd
		istore 3
		iload 3
		istore 100
		iload 100
		ireturn
	}
	static subvalues(I, I)I {
		sipush 10
		istore 4
		iload 0
		iload 1
		isub
		istore 2
		iload 2
		iload 4
		iadd
		istore 3
		iload 3
		istore 100
		iload 100
		ireturn
	}
	public static main([java/lang/String)V {
		sipush 5
		putstatic global_and_local_vars_4.addedValue I
		sipush 2
		sipush 4
		invokestatic global_and_local_vars_4.addvalues(I, I)I
		putstatic global_and_local_vars_4.myglobal1 I
		sipush 6
		sipush 8
		invokestatic global_and_local_vars_4.mulvalues(I, I)I
		putstatic global_and_local_vars_4.myglobal2 I
		sipush 8
		sipush 4
		invokestatic global_and_local_vars_4.subvalues(I, I)I
		putstatic global_and_local_vars_4.myglobal3 I
		getstatic java/lang/System.out java/io/PrintStream
		ldc "addedValue="
		invokevirtual java/io/PrintStream.print(java/lang/String)V
		getstatic java/lang/System.out java/io/PrintStream
		getstatic global_and_local_vars_4.addedValue I
		invokevirtual java/io/PrintStream.print(I)V
		getstatic java/lang/System.out java/io/PrintStream
		invokevirtual java/io/PrintStream.println()V
		getstatic java/lang/System.out java/io/PrintStream
		ldc "2+4 + addedValue="
		invokevirtual java/io/PrintStream.print(java/lang/String)V
		getstatic java/lang/System.out java/io/PrintStream
		getstatic global_and_local_vars_4.myglobal1 I
		invokevirtual java/io/PrintStream.print(I)V
		getstatic java/lang/System.out java/io/PrintStream
		invokevirtual java/io/PrintStream.println()V
		getstatic java/lang/System.out java/io/PrintStream
		ldc "6*8 + addedValue="
		invokevirtual java/io/PrintStream.print(java/lang/String)V
		getstatic java/lang/System.out java/io/PrintStream
		getstatic global_and_local_vars_4.myglobal2 I
		invokevirtual java/io/PrintStream.print(I)V
		getstatic java/lang/System.out java/io/PrintStream
		invokevirtual java/io/PrintStream.println()V
		getstatic java/lang/System.out java/io/PrintStream
		ldc "8-4 + local addedValue(10)="
		invokevirtual java/io/PrintStream.print(java/lang/String)V
		getstatic java/lang/System.out java/io/PrintStream
		getstatic global_and_local_vars_4.myglobal3 I
		invokevirtual java/io/PrintStream.print(I)V
		getstatic java/lang/System.out java/io/PrintStream
		invokevirtual java/io/PrintStream.println()V
		return
	}
}
