// Code generated by POJ 0.1
public class if_with_strings_without_and_or {
	public static main([java/lang/String)V {
		getstatic java/lang/System.out java/io/PrintStream
		ldc "aaa>bbb  must be false: "
		invokevirtual java/io/PrintStream.print(java/lang/String)V
		ldc "aaa"
		ldc "bbb"
		invokevirtual java/lang/String.compareTo(java/lang/String)I
		iflt L3
		iconst 1 
		goto L4
		L3:
		iconst 0 
		L4:
		ifeq L1
		getstatic java/lang/System.out java/io/PrintStream
		ldc "true"
		invokevirtual java/io/PrintStream.print(java/lang/String)V
		getstatic java/lang/System.out java/io/PrintStream
		invokevirtual java/io/PrintStream.println()V
		goto L2
		L1:
		getstatic java/lang/System.out java/io/PrintStream
		ldc "false"
		invokevirtual java/io/PrintStream.print(java/lang/String)V
		getstatic java/lang/System.out java/io/PrintStream
		invokevirtual java/io/PrintStream.println()V
		L2:
		getstatic java/lang/System.out java/io/PrintStream
		ldc "ccc>bbb must be true: "
		invokevirtual java/io/PrintStream.print(java/lang/String)V
		ldc "ccc"
		ldc "bbb"
		invokevirtual java/lang/String.compareTo(java/lang/String)I
		iflt L7
		iconst 1 
		goto L8
		L7:
		iconst 0 
		L8:
		ifeq L5
		getstatic java/lang/System.out java/io/PrintStream
		ldc "true"
		invokevirtual java/io/PrintStream.print(java/lang/String)V
		getstatic java/lang/System.out java/io/PrintStream
		invokevirtual java/io/PrintStream.println()V
		goto L6
		L5:
		getstatic java/lang/System.out java/io/PrintStream
		ldc "false"
		invokevirtual java/io/PrintStream.print(java/lang/String)V
		getstatic java/lang/System.out java/io/PrintStream
		invokevirtual java/io/PrintStream.println()V
		L6:
		getstatic java/lang/System.out java/io/PrintStream
		ldc "b>d must be false: "
		invokevirtual java/io/PrintStream.print(java/lang/String)V
		getstatic java/lang/System.out java/io/PrintStream
		invokevirtual java/io/PrintStream.println()V
		ldc "b"
		ldc "d"
		invokevirtual java/lang/String.compareTo(java/lang/String)I
		iflt L11
		iconst 1 
		goto L12
		L11:
		iconst 0 
		L12:
		ifeq L9
		getstatic java/lang/System.out java/io/PrintStream
		ldc "true"
		invokevirtual java/io/PrintStream.print(java/lang/String)V
		getstatic java/lang/System.out java/io/PrintStream
		invokevirtual java/io/PrintStream.println()V
		goto L10
		L9:
		L10:
		getstatic java/lang/System.out java/io/PrintStream
		ldc "d>b must be true: "
		invokevirtual java/io/PrintStream.print(java/lang/String)V
		ldc "d"
		ldc "b"
		invokevirtual java/lang/String.compareTo(java/lang/String)I
		iflt L15
		iconst 1 
		goto L16
		L15:
		iconst 0 
		L16:
		ifeq L13
		getstatic java/lang/System.out java/io/PrintStream
		ldc "true"
		invokevirtual java/io/PrintStream.print(java/lang/String)V
		getstatic java/lang/System.out java/io/PrintStream
		invokevirtual java/io/PrintStream.println()V
		goto L14
		L13:
		L14:
		getstatic java/lang/System.out java/io/PrintStream
		ldc "aaa<bbb must be true: "
		invokevirtual java/io/PrintStream.print(java/lang/String)V
		ldc "aaa"
		ldc "bbb"
		invokevirtual java/lang/String.compareTo(java/lang/String)I
		ifgt L19
		iconst 1 
		goto L20
		L19:
		iconst 0 
		L20:
		ifeq L17
		getstatic java/lang/System.out java/io/PrintStream
		ldc "true"
		invokevirtual java/io/PrintStream.print(java/lang/String)V
		getstatic java/lang/System.out java/io/PrintStream
		invokevirtual java/io/PrintStream.println()V
		goto L18
		L17:
		getstatic java/lang/System.out java/io/PrintStream
		ldc "false"
		invokevirtual java/io/PrintStream.print(java/lang/String)V
		getstatic java/lang/System.out java/io/PrintStream
		invokevirtual java/io/PrintStream.println()V
		L18:
		getstatic java/lang/System.out java/io/PrintStream
		ldc "bbb<aaa must be false: "
		invokevirtual java/io/PrintStream.print(java/lang/String)V
		ldc "bbb"
		ldc "aaa"
		invokevirtual java/lang/String.compareTo(java/lang/String)I
		ifgt L23
		iconst 1 
		goto L24
		L23:
		iconst 0 
		L24:
		ifeq L21
		getstatic java/lang/System.out java/io/PrintStream
		ldc "true"
		invokevirtual java/io/PrintStream.print(java/lang/String)V
		getstatic java/lang/System.out java/io/PrintStream
		invokevirtual java/io/PrintStream.println()V
		goto L22
		L21:
		getstatic java/lang/System.out java/io/PrintStream
		ldc "false"
		invokevirtual java/io/PrintStream.print(java/lang/String)V
		getstatic java/lang/System.out java/io/PrintStream
		invokevirtual java/io/PrintStream.println()V
		L22:
		getstatic java/lang/System.out java/io/PrintStream
		ldc "bbb>=aaa must be true: "
		invokevirtual java/io/PrintStream.print(java/lang/String)V
		ldc "bbb"
		ldc "aaa"
		invokevirtual java/lang/String.compareTo(java/lang/String)I
		iflt L27
		iconst 1 
		goto L28
		L27:
		iconst 0 
		L28:
		ifeq L25
		getstatic java/lang/System.out java/io/PrintStream
		ldc "true"
		invokevirtual java/io/PrintStream.print(java/lang/String)V
		getstatic java/lang/System.out java/io/PrintStream
		invokevirtual java/io/PrintStream.println()V
		goto L26
		L25:
		getstatic java/lang/System.out java/io/PrintStream
		ldc "false"
		invokevirtual java/io/PrintStream.print(java/lang/String)V
		getstatic java/lang/System.out java/io/PrintStream
		invokevirtual java/io/PrintStream.println()V
		L26:
		getstatic java/lang/System.out java/io/PrintStream
		ldc "aaa>=bbb  must be false: "
		invokevirtual java/io/PrintStream.print(java/lang/String)V
		ldc "aaa"
		ldc "bbb"
		invokevirtual java/lang/String.compareTo(java/lang/String)I
		iflt L31
		iconst 1 
		goto L32
		L31:
		iconst 0 
		L32:
		ifeq L29
		getstatic java/lang/System.out java/io/PrintStream
		ldc "true"
		invokevirtual java/io/PrintStream.print(java/lang/String)V
		getstatic java/lang/System.out java/io/PrintStream
		invokevirtual java/io/PrintStream.println()V
		goto L30
		L29:
		getstatic java/lang/System.out java/io/PrintStream
		ldc "false"
		invokevirtual java/io/PrintStream.print(java/lang/String)V
		getstatic java/lang/System.out java/io/PrintStream
		invokevirtual java/io/PrintStream.println()V
		L30:
		getstatic java/lang/System.out java/io/PrintStream
		ldc "aaa>=aaa must be true: "
		invokevirtual java/io/PrintStream.print(java/lang/String)V
		ldc "aaa"
		ldc "aaa"
		invokevirtual java/lang/String.compareTo(java/lang/String)I
		iflt L35
		iconst 1 
		goto L36
		L35:
		iconst 0 
		L36:
		ifeq L33
		getstatic java/lang/System.out java/io/PrintStream
		ldc "true"
		invokevirtual java/io/PrintStream.print(java/lang/String)V
		getstatic java/lang/System.out java/io/PrintStream
		invokevirtual java/io/PrintStream.println()V
		goto L34
		L33:
		getstatic java/lang/System.out java/io/PrintStream
		ldc "false"
		invokevirtual java/io/PrintStream.print(java/lang/String)V
		getstatic java/lang/System.out java/io/PrintStream
		invokevirtual java/io/PrintStream.println()V
		L34:
		getstatic java/lang/System.out java/io/PrintStream
		ldc "aaa<=bbb must be true: "
		invokevirtual java/io/PrintStream.print(java/lang/String)V
		ldc "aaa"
		ldc "bbb"
		invokevirtual java/lang/String.compareTo(java/lang/String)I
		ifgt L39
		iconst 1 
		goto L40
		L39:
		iconst 0 
		L40:
		ifeq L37
		getstatic java/lang/System.out java/io/PrintStream
		ldc "true"
		invokevirtual java/io/PrintStream.print(java/lang/String)V
		getstatic java/lang/System.out java/io/PrintStream
		invokevirtual java/io/PrintStream.println()V
		goto L38
		L37:
		getstatic java/lang/System.out java/io/PrintStream
		ldc "false"
		invokevirtual java/io/PrintStream.print(java/lang/String)V
		getstatic java/lang/System.out java/io/PrintStream
		invokevirtual java/io/PrintStream.println()V
		L38:
		getstatic java/lang/System.out java/io/PrintStream
		ldc "bbb<=aaa must be false: "
		invokevirtual java/io/PrintStream.print(java/lang/String)V
		ldc "bbb"
		ldc "aaa"
		invokevirtual java/lang/String.compareTo(java/lang/String)I
		ifgt L43
		iconst 1 
		goto L44
		L43:
		iconst 0 
		L44:
		ifeq L41
		getstatic java/lang/System.out java/io/PrintStream
		ldc "true"
		invokevirtual java/io/PrintStream.print(java/lang/String)V
		getstatic java/lang/System.out java/io/PrintStream
		invokevirtual java/io/PrintStream.println()V
		goto L42
		L41:
		getstatic java/lang/System.out java/io/PrintStream
		ldc "false"
		invokevirtual java/io/PrintStream.print(java/lang/String)V
		getstatic java/lang/System.out java/io/PrintStream
		invokevirtual java/io/PrintStream.println()V
		L42:
		getstatic java/lang/System.out java/io/PrintStream
		ldc "aaa<=aaa must be true: "
		invokevirtual java/io/PrintStream.print(java/lang/String)V
		ldc "aaa"
		ldc "aaa"
		invokevirtual java/lang/String.compareTo(java/lang/String)I
		ifgt L47
		iconst 1 
		goto L48
		L47:
		iconst 0 
		L48:
		ifeq L45
		getstatic java/lang/System.out java/io/PrintStream
		ldc "true"
		invokevirtual java/io/PrintStream.print(java/lang/String)V
		getstatic java/lang/System.out java/io/PrintStream
		invokevirtual java/io/PrintStream.println()V
		goto L46
		L45:
		getstatic java/lang/System.out java/io/PrintStream
		ldc "false"
		invokevirtual java/io/PrintStream.print(java/lang/String)V
		getstatic java/lang/System.out java/io/PrintStream
		invokevirtual java/io/PrintStream.println()V
		L46:
		getstatic java/lang/System.out java/io/PrintStream
		ldc "bbb=bbb must be true: "
		invokevirtual java/io/PrintStream.print(java/lang/String)V
		ldc "bbb"
		ldc "bbb"
		invokevirtual java/lang/String.compareTo(java/lang/String)I
		ifne L51
		iconst 1 
		goto L52
		L51:
		iconst 0 
		L52:
		ifeq L49
		getstatic java/lang/System.out java/io/PrintStream
		ldc "true"
		invokevirtual java/io/PrintStream.print(java/lang/String)V
		getstatic java/lang/System.out java/io/PrintStream
		invokevirtual java/io/PrintStream.println()V
		goto L50
		L49:
		getstatic java/lang/System.out java/io/PrintStream
		ldc "false"
		invokevirtual java/io/PrintStream.print(java/lang/String)V
		getstatic java/lang/System.out java/io/PrintStream
		invokevirtual java/io/PrintStream.println()V
		L50:
		getstatic java/lang/System.out java/io/PrintStream
		ldc "aaa=bbb must be false: "
		invokevirtual java/io/PrintStream.print(java/lang/String)V
		ldc "aaa"
		ldc "bbb"
		invokevirtual java/lang/String.compareTo(java/lang/String)I
		ifne L55
		iconst 1 
		goto L56
		L55:
		iconst 0 
		L56:
		ifeq L53
		getstatic java/lang/System.out java/io/PrintStream
		ldc "true"
		invokevirtual java/io/PrintStream.print(java/lang/String)V
		getstatic java/lang/System.out java/io/PrintStream
		invokevirtual java/io/PrintStream.println()V
		goto L54
		L53:
		getstatic java/lang/System.out java/io/PrintStream
		ldc "false"
		invokevirtual java/io/PrintStream.print(java/lang/String)V
		getstatic java/lang/System.out java/io/PrintStream
		invokevirtual java/io/PrintStream.println()V
		L54:
		getstatic java/lang/System.out java/io/PrintStream
		ldc "aaa<>bbb must be true: "
		invokevirtual java/io/PrintStream.print(java/lang/String)V
		ldc "aaa"
		ldc "bbb"
		invokevirtual java/lang/String.compareTo(java/lang/String)I
		ifeq L59
		iconst 1 
		goto L60
		L59:
		iconst 0 
		L60:
		ifeq L57
		getstatic java/lang/System.out java/io/PrintStream
		ldc "true"
		invokevirtual java/io/PrintStream.print(java/lang/String)V
		getstatic java/lang/System.out java/io/PrintStream
		invokevirtual java/io/PrintStream.println()V
		goto L58
		L57:
		getstatic java/lang/System.out java/io/PrintStream
		ldc "false"
		invokevirtual java/io/PrintStream.print(java/lang/String)V
		getstatic java/lang/System.out java/io/PrintStream
		invokevirtual java/io/PrintStream.println()V
		L58:
		getstatic java/lang/System.out java/io/PrintStream
		ldc "aaa<>aaa must be false: "
		invokevirtual java/io/PrintStream.print(java/lang/String)V
		ldc "aaa"
		ldc "aaa"
		invokevirtual java/lang/String.compareTo(java/lang/String)I
		ifeq L63
		iconst 1 
		goto L64
		L63:
		iconst 0 
		L64:
		ifeq L61
		getstatic java/lang/System.out java/io/PrintStream
		ldc "true"
		invokevirtual java/io/PrintStream.print(java/lang/String)V
		getstatic java/lang/System.out java/io/PrintStream
		invokevirtual java/io/PrintStream.println()V
		goto L62
		L61:
		getstatic java/lang/System.out java/io/PrintStream
		ldc "false"
		invokevirtual java/io/PrintStream.print(java/lang/String)V
		getstatic java/lang/System.out java/io/PrintStream
		invokevirtual java/io/PrintStream.println()V
		L62:
		return
	}
}
