// Code generated by POJ 0.1
public class if_with_strings_with_and_or {
	public static main([java/lang/String)V {
		getstatic java/lang/System.out java/io/PrintStream
		ldc "b>a must be true: "
		invokevirtual java/io/PrintStream.print(java/lang/String)V
		ldc "b"
		ldc "a"
		invokevirtual java/lang/String.compareTo(java/lang/String)I
		iflt L3
		iconst 1 
		goto L4
		L3:
		iconst 0 
		L4:
		ifeq L1
		getstatic java/lang/System.out java/io/PrintStream
		ldc "true"
		invokevirtual java/io/PrintStream.print(java/lang/String)V
		getstatic java/lang/System.out java/io/PrintStream
		invokevirtual java/io/PrintStream.println()V
		goto L2
		L1:
		getstatic java/lang/System.out java/io/PrintStream
		ldc "false"
		invokevirtual java/io/PrintStream.print(java/lang/String)V
		getstatic java/lang/System.out java/io/PrintStream
		invokevirtual java/io/PrintStream.println()V
		L2:
		getstatic java/lang/System.out java/io/PrintStream
		ldc "a>b must be false: "
		invokevirtual java/io/PrintStream.print(java/lang/String)V
		ldc "a"
		ldc "b"
		invokevirtual java/lang/String.compareTo(java/lang/String)I
		iflt L7
		iconst 1 
		goto L8
		L7:
		iconst 0 
		L8:
		ifeq L5
		getstatic java/lang/System.out java/io/PrintStream
		ldc "true"
		invokevirtual java/io/PrintStream.print(java/lang/String)V
		getstatic java/lang/System.out java/io/PrintStream
		invokevirtual java/io/PrintStream.println()V
		goto L6
		L5:
		getstatic java/lang/System.out java/io/PrintStream
		ldc "false"
		invokevirtual java/io/PrintStream.print(java/lang/String)V
		getstatic java/lang/System.out java/io/PrintStream
		invokevirtual java/io/PrintStream.println()V
		L6:
		getstatic java/lang/System.out java/io/PrintStream
		ldc "aaa>bbb and bbb>ccc must be false: "
		invokevirtual java/io/PrintStream.print(java/lang/String)V
		ldc "aaa"
		ldc "bbb"
		invokevirtual java/lang/String.compareTo(java/lang/String)I
		iflt L11
		iconst 1 
		goto L12
		L11:
		iconst 0 
		L12:
		ldc "bbb"
		ldc "ccc"
		invokevirtual java/lang/String.compareTo(java/lang/String)I
		iflt L13
		iconst 1 
		goto L14
		L13:
		iconst 0 
		L14:
		iand 
		ifeq L9
		getstatic java/lang/System.out java/io/PrintStream
		ldc "true"
		invokevirtual java/io/PrintStream.print(java/lang/String)V
		getstatic java/lang/System.out java/io/PrintStream
		invokevirtual java/io/PrintStream.println()V
		goto L10
		L9:
		getstatic java/lang/System.out java/io/PrintStream
		ldc "false"
		invokevirtual java/io/PrintStream.print(java/lang/String)V
		getstatic java/lang/System.out java/io/PrintStream
		invokevirtual java/io/PrintStream.println()V
		L10:
		getstatic java/lang/System.out java/io/PrintStream
		ldc "aaa<bbb and bbb<ccc must be true: "
		invokevirtual java/io/PrintStream.print(java/lang/String)V
		ldc "aaa"
		ldc "bbb"
		invokevirtual java/lang/String.compareTo(java/lang/String)I
		ifgt L17
		iconst 1 
		goto L18
		L17:
		iconst 0 
		L18:
		ldc "bbb"
		ldc "ccc"
		invokevirtual java/lang/String.compareTo(java/lang/String)I
		ifgt L19
		iconst 1 
		goto L20
		L19:
		iconst 0 
		L20:
		iand 
		ifeq L15
		getstatic java/lang/System.out java/io/PrintStream
		ldc "true"
		invokevirtual java/io/PrintStream.print(java/lang/String)V
		getstatic java/lang/System.out java/io/PrintStream
		invokevirtual java/io/PrintStream.println()V
		goto L16
		L15:
		getstatic java/lang/System.out java/io/PrintStream
		ldc "false"
		invokevirtual java/io/PrintStream.print(java/lang/String)V
		getstatic java/lang/System.out java/io/PrintStream
		invokevirtual java/io/PrintStream.println()V
		L16:
		getstatic java/lang/System.out java/io/PrintStream
		ldc "aaa>bbb and bbb<ccc must be false: "
		invokevirtual java/io/PrintStream.print(java/lang/String)V
		ldc "aaa"
		ldc "bbb"
		invokevirtual java/lang/String.compareTo(java/lang/String)I
		iflt L23
		iconst 1 
		goto L24
		L23:
		iconst 0 
		L24:
		ldc "bbb"
		ldc "ccc"
		invokevirtual java/lang/String.compareTo(java/lang/String)I
		ifgt L25
		iconst 1 
		goto L26
		L25:
		iconst 0 
		L26:
		iand 
		ifeq L21
		getstatic java/lang/System.out java/io/PrintStream
		ldc "true"
		invokevirtual java/io/PrintStream.print(java/lang/String)V
		getstatic java/lang/System.out java/io/PrintStream
		invokevirtual java/io/PrintStream.println()V
		goto L22
		L21:
		getstatic java/lang/System.out java/io/PrintStream
		ldc "false"
		invokevirtual java/io/PrintStream.print(java/lang/String)V
		getstatic java/lang/System.out java/io/PrintStream
		invokevirtual java/io/PrintStream.println()V
		L22:
		getstatic java/lang/System.out java/io/PrintStream
		ldc "aaa<bbb and bbb>ccc must be false: "
		invokevirtual java/io/PrintStream.print(java/lang/String)V
		ldc "aaa"
		ldc "bbb"
		invokevirtual java/lang/String.compareTo(java/lang/String)I
		ifgt L29
		iconst 1 
		goto L30
		L29:
		iconst 0 
		L30:
		ldc "bbb"
		ldc "ccc"
		invokevirtual java/lang/String.compareTo(java/lang/String)I
		iflt L31
		iconst 1 
		goto L32
		L31:
		iconst 0 
		L32:
		iand 
		ifeq L27
		getstatic java/lang/System.out java/io/PrintStream
		ldc "true"
		invokevirtual java/io/PrintStream.print(java/lang/String)V
		getstatic java/lang/System.out java/io/PrintStream
		invokevirtual java/io/PrintStream.println()V
		goto L28
		L27:
		getstatic java/lang/System.out java/io/PrintStream
		ldc "false"
		invokevirtual java/io/PrintStream.print(java/lang/String)V
		getstatic java/lang/System.out java/io/PrintStream
		invokevirtual java/io/PrintStream.println()V
		L28:
		getstatic java/lang/System.out java/io/PrintStream
		ldc "aaa>bbb or bbb>ccc must be false: "
		invokevirtual java/io/PrintStream.print(java/lang/String)V
		ldc "aaa"
		ldc "bbb"
		invokevirtual java/lang/String.compareTo(java/lang/String)I
		iflt L35
		iconst 1 
		goto L36
		L35:
		iconst 0 
		L36:
		ldc "bbb"
		ldc "ccc"
		invokevirtual java/lang/String.compareTo(java/lang/String)I
		iflt L37
		iconst 1 
		goto L38
		L37:
		iconst 0 
		L38:
		ior 
		ifeq L33
		getstatic java/lang/System.out java/io/PrintStream
		ldc "true"
		invokevirtual java/io/PrintStream.print(java/lang/String)V
		getstatic java/lang/System.out java/io/PrintStream
		invokevirtual java/io/PrintStream.println()V
		goto L34
		L33:
		getstatic java/lang/System.out java/io/PrintStream
		ldc "false"
		invokevirtual java/io/PrintStream.print(java/lang/String)V
		getstatic java/lang/System.out java/io/PrintStream
		invokevirtual java/io/PrintStream.println()V
		L34:
		getstatic java/lang/System.out java/io/PrintStream
		ldc "aaa<bbb or bbb<ccc must be true: "
		invokevirtual java/io/PrintStream.print(java/lang/String)V
		ldc "aaa"
		ldc "bbb"
		invokevirtual java/lang/String.compareTo(java/lang/String)I
		ifgt L41
		iconst 1 
		goto L42
		L41:
		iconst 0 
		L42:
		ldc "bbb"
		ldc "ccc"
		invokevirtual java/lang/String.compareTo(java/lang/String)I
		ifgt L43
		iconst 1 
		goto L44
		L43:
		iconst 0 
		L44:
		ior 
		ifeq L39
		getstatic java/lang/System.out java/io/PrintStream
		ldc "true"
		invokevirtual java/io/PrintStream.print(java/lang/String)V
		getstatic java/lang/System.out java/io/PrintStream
		invokevirtual java/io/PrintStream.println()V
		goto L40
		L39:
		getstatic java/lang/System.out java/io/PrintStream
		ldc "false"
		invokevirtual java/io/PrintStream.print(java/lang/String)V
		getstatic java/lang/System.out java/io/PrintStream
		invokevirtual java/io/PrintStream.println()V
		L40:
		getstatic java/lang/System.out java/io/PrintStream
		ldc "aaa>bbb or bbb<ccc must be true: "
		invokevirtual java/io/PrintStream.print(java/lang/String)V
		ldc "aaa"
		ldc "bbb"
		invokevirtual java/lang/String.compareTo(java/lang/String)I
		iflt L47
		iconst 1 
		goto L48
		L47:
		iconst 0 
		L48:
		ldc "bbb"
		ldc "ccc"
		invokevirtual java/lang/String.compareTo(java/lang/String)I
		ifgt L49
		iconst 1 
		goto L50
		L49:
		iconst 0 
		L50:
		ior 
		ifeq L45
		getstatic java/lang/System.out java/io/PrintStream
		ldc "true"
		invokevirtual java/io/PrintStream.print(java/lang/String)V
		getstatic java/lang/System.out java/io/PrintStream
		invokevirtual java/io/PrintStream.println()V
		goto L46
		L45:
		getstatic java/lang/System.out java/io/PrintStream
		ldc "false"
		invokevirtual java/io/PrintStream.print(java/lang/String)V
		getstatic java/lang/System.out java/io/PrintStream
		invokevirtual java/io/PrintStream.println()V
		L46:
		getstatic java/lang/System.out java/io/PrintStream
		ldc "aaa<bbb or bbb>ccc must be true: "
		invokevirtual java/io/PrintStream.print(java/lang/String)V
		ldc "aaa"
		ldc "bbb"
		invokevirtual java/lang/String.compareTo(java/lang/String)I
		ifgt L53
		iconst 1 
		goto L54
		L53:
		iconst 0 
		L54:
		ldc "bbb"
		ldc "ccc"
		invokevirtual java/lang/String.compareTo(java/lang/String)I
		iflt L55
		iconst 1 
		goto L56
		L55:
		iconst 0 
		L56:
		ior 
		ifeq L51
		getstatic java/lang/System.out java/io/PrintStream
		ldc "true"
		invokevirtual java/io/PrintStream.print(java/lang/String)V
		getstatic java/lang/System.out java/io/PrintStream
		invokevirtual java/io/PrintStream.println()V
		goto L52
		L51:
		getstatic java/lang/System.out java/io/PrintStream
		ldc "false"
		invokevirtual java/io/PrintStream.print(java/lang/String)V
		getstatic java/lang/System.out java/io/PrintStream
		invokevirtual java/io/PrintStream.println()V
		L52:
		return
	}
}
