// Code generated by POJ 0.1
public class if_with_integers_without_and_or {
	public static main([java/lang/String)V {
		getstatic java/lang/System.out java/io/PrintStream
		ldc "111>222  must be false: "
		invokevirtual java/io/PrintStream.print(java/lang/String)V
		sipush 111
		sipush 222
		if_icmple L4
		iconst 1 
		goto L5
		L4:
		iconst 0 
		L5:
		ifeq L1
		getstatic java/lang/System.out java/io/PrintStream
		ldc "true"
		invokevirtual java/io/PrintStream.print(java/lang/String)V
		getstatic java/lang/System.out java/io/PrintStream
		invokevirtual java/io/PrintStream.println()V
		goto L2
		L1:
		getstatic java/lang/System.out java/io/PrintStream
		ldc "false"
		invokevirtual java/io/PrintStream.print(java/lang/String)V
		getstatic java/lang/System.out java/io/PrintStream
		invokevirtual java/io/PrintStream.println()V
		L2:
		getstatic java/lang/System.out java/io/PrintStream
		ldc "333>222 must be true: "
		invokevirtual java/io/PrintStream.print(java/lang/String)V
		sipush 333
		sipush 222
		if_icmple L9
		iconst 1 
		goto L10
		L9:
		iconst 0 
		L10:
		ifeq L6
		getstatic java/lang/System.out java/io/PrintStream
		ldc "true"
		invokevirtual java/io/PrintStream.print(java/lang/String)V
		getstatic java/lang/System.out java/io/PrintStream
		invokevirtual java/io/PrintStream.println()V
		goto L7
		L6:
		getstatic java/lang/System.out java/io/PrintStream
		ldc "false"
		invokevirtual java/io/PrintStream.print(java/lang/String)V
		getstatic java/lang/System.out java/io/PrintStream
		invokevirtual java/io/PrintStream.println()V
		L7:
		getstatic java/lang/System.out java/io/PrintStream
		ldc "2>4 must be false: "
		invokevirtual java/io/PrintStream.print(java/lang/String)V
		getstatic java/lang/System.out java/io/PrintStream
		invokevirtual java/io/PrintStream.println()V
		sipush 2
		sipush 4
		if_icmple L14
		iconst 1 
		goto L15
		L14:
		iconst 0 
		L15:
		ifeq L11
		getstatic java/lang/System.out java/io/PrintStream
		ldc "true"
		invokevirtual java/io/PrintStream.print(java/lang/String)V
		getstatic java/lang/System.out java/io/PrintStream
		invokevirtual java/io/PrintStream.println()V
		goto L12
		L11:
		L12:
		getstatic java/lang/System.out java/io/PrintStream
		ldc "4>2 must be true: "
		invokevirtual java/io/PrintStream.print(java/lang/String)V
		sipush 4
		sipush 2
		if_icmple L19
		iconst 1 
		goto L20
		L19:
		iconst 0 
		L20:
		ifeq L16
		getstatic java/lang/System.out java/io/PrintStream
		ldc "true"
		invokevirtual java/io/PrintStream.print(java/lang/String)V
		getstatic java/lang/System.out java/io/PrintStream
		invokevirtual java/io/PrintStream.println()V
		goto L17
		L16:
		L17:
		getstatic java/lang/System.out java/io/PrintStream
		ldc "111<222 must be true: "
		invokevirtual java/io/PrintStream.print(java/lang/String)V
		sipush 111
		sipush 222
		if_icmpge L24
		iconst 1 
		goto L25
		L24:
		iconst 0 
		L25:
		ifeq L21
		getstatic java/lang/System.out java/io/PrintStream
		ldc "true"
		invokevirtual java/io/PrintStream.print(java/lang/String)V
		getstatic java/lang/System.out java/io/PrintStream
		invokevirtual java/io/PrintStream.println()V
		goto L22
		L21:
		getstatic java/lang/System.out java/io/PrintStream
		ldc "false"
		invokevirtual java/io/PrintStream.print(java/lang/String)V
		getstatic java/lang/System.out java/io/PrintStream
		invokevirtual java/io/PrintStream.println()V
		L22:
		getstatic java/lang/System.out java/io/PrintStream
		ldc "222<111 must be false: "
		invokevirtual java/io/PrintStream.print(java/lang/String)V
		sipush 222
		sipush 111
		if_icmpge L29
		iconst 1 
		goto L30
		L29:
		iconst 0 
		L30:
		ifeq L26
		getstatic java/lang/System.out java/io/PrintStream
		ldc "true"
		invokevirtual java/io/PrintStream.print(java/lang/String)V
		getstatic java/lang/System.out java/io/PrintStream
		invokevirtual java/io/PrintStream.println()V
		goto L27
		L26:
		getstatic java/lang/System.out java/io/PrintStream
		ldc "false"
		invokevirtual java/io/PrintStream.print(java/lang/String)V
		getstatic java/lang/System.out java/io/PrintStream
		invokevirtual java/io/PrintStream.println()V
		L27:
		getstatic java/lang/System.out java/io/PrintStream
		ldc "222>=111 must be true: "
		invokevirtual java/io/PrintStream.print(java/lang/String)V
		sipush 222
		sipush 111
		if_icmplt L34
		iconst 1 
		goto L35
		L34:
		iconst 0 
		L35:
		ifeq L31
		getstatic java/lang/System.out java/io/PrintStream
		ldc "true"
		invokevirtual java/io/PrintStream.print(java/lang/String)V
		getstatic java/lang/System.out java/io/PrintStream
		invokevirtual java/io/PrintStream.println()V
		goto L32
		L31:
		getstatic java/lang/System.out java/io/PrintStream
		ldc "false"
		invokevirtual java/io/PrintStream.print(java/lang/String)V
		getstatic java/lang/System.out java/io/PrintStream
		invokevirtual java/io/PrintStream.println()V
		L32:
		getstatic java/lang/System.out java/io/PrintStream
		ldc "111>=222  must be false: "
		invokevirtual java/io/PrintStream.print(java/lang/String)V
		sipush 111
		sipush 222
		if_icmplt L39
		iconst 1 
		goto L40
		L39:
		iconst 0 
		L40:
		ifeq L36
		getstatic java/lang/System.out java/io/PrintStream
		ldc "true"
		invokevirtual java/io/PrintStream.print(java/lang/String)V
		getstatic java/lang/System.out java/io/PrintStream
		invokevirtual java/io/PrintStream.println()V
		goto L37
		L36:
		getstatic java/lang/System.out java/io/PrintStream
		ldc "false"
		invokevirtual java/io/PrintStream.print(java/lang/String)V
		getstatic java/lang/System.out java/io/PrintStream
		invokevirtual java/io/PrintStream.println()V
		L37:
		getstatic java/lang/System.out java/io/PrintStream
		ldc "111>=111 must be true: "
		invokevirtual java/io/PrintStream.print(java/lang/String)V
		sipush 111
		sipush 111
		if_icmplt L44
		iconst 1 
		goto L45
		L44:
		iconst 0 
		L45:
		ifeq L41
		getstatic java/lang/System.out java/io/PrintStream
		ldc "true"
		invokevirtual java/io/PrintStream.print(java/lang/String)V
		getstatic java/lang/System.out java/io/PrintStream
		invokevirtual java/io/PrintStream.println()V
		goto L42
		L41:
		getstatic java/lang/System.out java/io/PrintStream
		ldc "false"
		invokevirtual java/io/PrintStream.print(java/lang/String)V
		getstatic java/lang/System.out java/io/PrintStream
		invokevirtual java/io/PrintStream.println()V
		L42:
		getstatic java/lang/System.out java/io/PrintStream
		ldc "111<=222 must be true: "
		invokevirtual java/io/PrintStream.print(java/lang/String)V
		sipush 111
		sipush 222
		if_icmpgt L49
		iconst 1 
		goto L50
		L49:
		iconst 0 
		L50:
		ifeq L46
		getstatic java/lang/System.out java/io/PrintStream
		ldc "true"
		invokevirtual java/io/PrintStream.print(java/lang/String)V
		getstatic java/lang/System.out java/io/PrintStream
		invokevirtual java/io/PrintStream.println()V
		goto L47
		L46:
		getstatic java/lang/System.out java/io/PrintStream
		ldc "false"
		invokevirtual java/io/PrintStream.print(java/lang/String)V
		getstatic java/lang/System.out java/io/PrintStream
		invokevirtual java/io/PrintStream.println()V
		L47:
		getstatic java/lang/System.out java/io/PrintStream
		ldc "222<=111 must be false: "
		invokevirtual java/io/PrintStream.print(java/lang/String)V
		sipush 222
		sipush 111
		if_icmpgt L54
		iconst 1 
		goto L55
		L54:
		iconst 0 
		L55:
		ifeq L51
		getstatic java/lang/System.out java/io/PrintStream
		ldc "true"
		invokevirtual java/io/PrintStream.print(java/lang/String)V
		getstatic java/lang/System.out java/io/PrintStream
		invokevirtual java/io/PrintStream.println()V
		goto L52
		L51:
		getstatic java/lang/System.out java/io/PrintStream
		ldc "false"
		invokevirtual java/io/PrintStream.print(java/lang/String)V
		getstatic java/lang/System.out java/io/PrintStream
		invokevirtual java/io/PrintStream.println()V
		L52:
		getstatic java/lang/System.out java/io/PrintStream
		ldc "111<=111 must be true: "
		invokevirtual java/io/PrintStream.print(java/lang/String)V
		sipush 111
		sipush 111
		if_icmpgt L59
		iconst 1 
		goto L60
		L59:
		iconst 0 
		L60:
		ifeq L56
		getstatic java/lang/System.out java/io/PrintStream
		ldc "true"
		invokevirtual java/io/PrintStream.print(java/lang/String)V
		getstatic java/lang/System.out java/io/PrintStream
		invokevirtual java/io/PrintStream.println()V
		goto L57
		L56:
		getstatic java/lang/System.out java/io/PrintStream
		ldc "false"
		invokevirtual java/io/PrintStream.print(java/lang/String)V
		getstatic java/lang/System.out java/io/PrintStream
		invokevirtual java/io/PrintStream.println()V
		L57:
		getstatic java/lang/System.out java/io/PrintStream
		ldc "222=222 must be true: "
		invokevirtual java/io/PrintStream.print(java/lang/String)V
		sipush 222
		sipush 222
		if_icmpne L64
		iconst 1 
		goto L65
		L64:
		iconst 0 
		L65:
		ifeq L61
		getstatic java/lang/System.out java/io/PrintStream
		ldc "true"
		invokevirtual java/io/PrintStream.print(java/lang/String)V
		getstatic java/lang/System.out java/io/PrintStream
		invokevirtual java/io/PrintStream.println()V
		goto L62
		L61:
		getstatic java/lang/System.out java/io/PrintStream
		ldc "false"
		invokevirtual java/io/PrintStream.print(java/lang/String)V
		getstatic java/lang/System.out java/io/PrintStream
		invokevirtual java/io/PrintStream.println()V
		L62:
		getstatic java/lang/System.out java/io/PrintStream
		ldc "111=222 must be false: "
		invokevirtual java/io/PrintStream.print(java/lang/String)V
		sipush 111
		sipush 222
		if_icmpne L69
		iconst 1 
		goto L70
		L69:
		iconst 0 
		L70:
		ifeq L66
		getstatic java/lang/System.out java/io/PrintStream
		ldc "true"
		invokevirtual java/io/PrintStream.print(java/lang/String)V
		getstatic java/lang/System.out java/io/PrintStream
		invokevirtual java/io/PrintStream.println()V
		goto L67
		L66:
		getstatic java/lang/System.out java/io/PrintStream
		ldc "false"
		invokevirtual java/io/PrintStream.print(java/lang/String)V
		getstatic java/lang/System.out java/io/PrintStream
		invokevirtual java/io/PrintStream.println()V
		L67:
		getstatic java/lang/System.out java/io/PrintStream
		ldc "111<>222 must be true: "
		invokevirtual java/io/PrintStream.print(java/lang/String)V
		sipush 111
		sipush 222
		if_icmpeq L74
		iconst 1 
		goto L75
		L74:
		iconst 0 
		L75:
		ifeq L71
		getstatic java/lang/System.out java/io/PrintStream
		ldc "true"
		invokevirtual java/io/PrintStream.print(java/lang/String)V
		getstatic java/lang/System.out java/io/PrintStream
		invokevirtual java/io/PrintStream.println()V
		goto L72
		L71:
		getstatic java/lang/System.out java/io/PrintStream
		ldc "false"
		invokevirtual java/io/PrintStream.print(java/lang/String)V
		getstatic java/lang/System.out java/io/PrintStream
		invokevirtual java/io/PrintStream.println()V
		L72:
		getstatic java/lang/System.out java/io/PrintStream
		ldc "111<>111 must be false: "
		invokevirtual java/io/PrintStream.print(java/lang/String)V
		sipush 111
		sipush 111
		if_icmpeq L79
		iconst 1 
		goto L80
		L79:
		iconst 0 
		L80:
		ifeq L76
		getstatic java/lang/System.out java/io/PrintStream
		ldc "true"
		invokevirtual java/io/PrintStream.print(java/lang/String)V
		getstatic java/lang/System.out java/io/PrintStream
		invokevirtual java/io/PrintStream.println()V
		goto L77
		L76:
		getstatic java/lang/System.out java/io/PrintStream
		ldc "false"
		invokevirtual java/io/PrintStream.print(java/lang/String)V
		getstatic java/lang/System.out java/io/PrintStream
		invokevirtual java/io/PrintStream.println()V
		L77:
		return
	}
}
