// Code generated by POJ 0.1
public class name_and_age {
	public static myname java/lang/String
	public static myage I
	public static main([java/lang/String)V {
		getstatic java/lang/System.out java/io/PrintStream
		ldc "What is your name? "
		invokevirtual java/io/PrintStream.print(java/lang/String)V
		invokestatic java/lang/System.console()java/io/Console
		invokevirtual java/io/Console.readLine()java/lang/String
		putstatic name_and_age.myname java/lang/String
		getstatic java/lang/System.out java/io/PrintStream
		ldc "How old are you? "
		invokevirtual java/io/PrintStream.print(java/lang/String)V
		invokestatic java/lang/System.console()java/io/Console
		invokevirtual java/io/Console.readLine()java/lang/String
		invokestatic java/lang/Integer.parseInt(java/lang/String)I
		putstatic name_and_age.myage I
		getstatic java/lang/System.out java/io/PrintStream
		invokevirtual java/io/PrintStream.println()V
		getstatic java/lang/System.out java/io/PrintStream
		ldc "Hello "
		invokevirtual java/io/PrintStream.print(java/lang/String)V
		getstatic java/lang/System.out java/io/PrintStream
		getstatic name_and_age.myname java/lang/String
		invokevirtual java/io/PrintStream.print(java/lang/String)V
		getstatic java/lang/System.out java/io/PrintStream
		invokevirtual java/io/PrintStream.println()V
		getstatic java/lang/System.out java/io/PrintStream
		ldc "You are "
		invokevirtual java/io/PrintStream.print(java/lang/String)V
		getstatic java/lang/System.out java/io/PrintStream
		getstatic name_and_age.myage I
		invokevirtual java/io/PrintStream.print(I)V
		getstatic java/lang/System.out java/io/PrintStream
		ldc " years old"
		invokevirtual java/io/PrintStream.print(java/lang/String)V
		getstatic java/lang/System.out java/io/PrintStream
		invokevirtual java/io/PrintStream.println()V
		return
	}
}
