// Code generated by POJ 0.1
public class nested_ifs {
	public static main([java/lang/String)V {
		sipush 1
		sipush 2
		if_icmple L1
		iconst 1 
		goto L2
		L1:
		iconst 0 
		L2:
		ifeq L101
		sipush 2
		sipush 3
		if_icmple L3
		iconst 1 
		goto L4
		L3:
		iconst 0 
		L4:
		ifeq L104
		getstatic java/lang/System.out java/io/PrintStream
		ldc "1 > 2 and 2 > 3"
		invokevirtual java/io/PrintStream.print(java/lang/String)V
		getstatic java/lang/System.out java/io/PrintStream
		invokevirtual java/io/PrintStream.println()V
		goto L105
		L104:
		getstatic java/lang/System.out java/io/PrintStream
		ldc "1 > 2 and 2 <= 3"
		invokevirtual java/io/PrintStream.print(java/lang/String)V
		getstatic java/lang/System.out java/io/PrintStream
		invokevirtual java/io/PrintStream.println()V
		L105:
		goto L102
		L101:
		getstatic java/lang/System.out java/io/PrintStream
		ldc "1 <= 2"
		invokevirtual java/io/PrintStream.print(java/lang/String)V
		getstatic java/lang/System.out java/io/PrintStream
		invokevirtual java/io/PrintStream.println()V
		L102:
		sipush 1
		sipush 2
		if_icmpge L5
		iconst 1 
		goto L6
		L5:
		iconst 0 
		L6:
		ifeq L107
		sipush 2
		sipush 3
		if_icmpge L7
		iconst 1 
		goto L8
		L7:
		iconst 0 
		L8:
		ifeq L110
		getstatic java/lang/System.out java/io/PrintStream
		ldc "1 < 2 and 2 < 3"
		invokevirtual java/io/PrintStream.print(java/lang/String)V
		getstatic java/lang/System.out java/io/PrintStream
		invokevirtual java/io/PrintStream.println()V
		goto L111
		L110:
		getstatic java/lang/System.out java/io/PrintStream
		ldc "1 < 2 and 2 >= 3"
		invokevirtual java/io/PrintStream.print(java/lang/String)V
		getstatic java/lang/System.out java/io/PrintStream
		invokevirtual java/io/PrintStream.println()V
		L111:
		goto L108
		L107:
		getstatic java/lang/System.out java/io/PrintStream
		ldc "1 >= 2"
		invokevirtual java/io/PrintStream.print(java/lang/String)V
		getstatic java/lang/System.out java/io/PrintStream
		invokevirtual java/io/PrintStream.println()V
		L108:
		sipush 1
		sipush 2
		if_icmpge L9
		iconst 1 
		goto L10
		L9:
		iconst 0 
		L10:
		ifeq L113
		sipush 2
		sipush 3
		if_icmple L11
		iconst 1 
		goto L12
		L11:
		iconst 0 
		L12:
		ifeq L116
		getstatic java/lang/System.out java/io/PrintStream
		ldc "1 < 2 and 2 > 3"
		invokevirtual java/io/PrintStream.print(java/lang/String)V
		getstatic java/lang/System.out java/io/PrintStream
		invokevirtual java/io/PrintStream.println()V
		goto L117
		L116:
		getstatic java/lang/System.out java/io/PrintStream
		ldc "1 < 2 and 2 <= 3"
		invokevirtual java/io/PrintStream.print(java/lang/String)V
		getstatic java/lang/System.out java/io/PrintStream
		invokevirtual java/io/PrintStream.println()V
		L117:
		goto L114
		L113:
		getstatic java/lang/System.out java/io/PrintStream
		ldc "1 >= 2"
		invokevirtual java/io/PrintStream.print(java/lang/String)V
		getstatic java/lang/System.out java/io/PrintStream
		invokevirtual java/io/PrintStream.println()V
		L114:
		sipush 1
		sipush 2
		if_icmple L13
		iconst 1 
		goto L14
		L13:
		iconst 0 
		L14:
		ifeq L119
		sipush 2
		sipush 3
		if_icmple L15
		iconst 1 
		goto L16
		L15:
		iconst 0 
		L16:
		ifeq L122
		getstatic java/lang/System.out java/io/PrintStream
		ldc "1 > 2 and 2 > 3"
		invokevirtual java/io/PrintStream.print(java/lang/String)V
		getstatic java/lang/System.out java/io/PrintStream
		invokevirtual java/io/PrintStream.println()V
		goto L123
		L122:
		getstatic java/lang/System.out java/io/PrintStream
		ldc "1 > 2 and 2 <= 3"
		invokevirtual java/io/PrintStream.print(java/lang/String)V
		getstatic java/lang/System.out java/io/PrintStream
		invokevirtual java/io/PrintStream.println()V
		L123:
		goto L120
		L119:
		sipush 1
		sipush 2
		if_icmpge L17
		iconst 1 
		goto L18
		L17:
		iconst 0 
		L18:
		ifeq L125
		sipush 2
		sipush 3
		if_icmpge L19
		iconst 1 
		goto L20
		L19:
		iconst 0 
		L20:
		ifeq L128
		getstatic java/lang/System.out java/io/PrintStream
		ldc "1 < 2 and 2 < 3"
		invokevirtual java/io/PrintStream.print(java/lang/String)V
		getstatic java/lang/System.out java/io/PrintStream
		invokevirtual java/io/PrintStream.println()V
		goto L129
		L128:
		getstatic java/lang/System.out java/io/PrintStream
		ldc "1 < 2 and 2 >= 3"
		invokevirtual java/io/PrintStream.print(java/lang/String)V
		getstatic java/lang/System.out java/io/PrintStream
		invokevirtual java/io/PrintStream.println()V
		L129:
		goto L126
		L125:
		L126:
		L120:
		return
	}
}
