// Code generated by POJ 0.1
public class operator_precedence {
	public static main([java/lang/String)V {
		getstatic java/lang/System.out java/io/PrintStream
		ldc "Resultado esperado eh 30: "
		invokevirtual java/io/PrintStream.print(java/lang/String)V
		getstatic java/lang/System.out java/io/PrintStream
		sipush 8
		sipush 4
		imul
		sipush 2
		isub
		invokevirtual java/io/PrintStream.print(I)V
		getstatic java/lang/System.out java/io/PrintStream
		invokevirtual java/io/PrintStream.println()V
		getstatic java/lang/System.out java/io/PrintStream
		ldc "Resultado esperado eh 2: "
		invokevirtual java/io/PrintStream.print(java/lang/String)V
		getstatic java/lang/System.out java/io/PrintStream
		sipush 10
		sipush 4
		sipush 2
		imul
		isub
		invokevirtual java/io/PrintStream.print(I)V
		getstatic java/lang/System.out java/io/PrintStream
		invokevirtual java/io/PrintStream.println()V
		getstatic java/lang/System.out java/io/PrintStream
		ldc "Resultado esperado eh 2: "
		invokevirtual java/io/PrintStream.print(java/lang/String)V
		getstatic java/lang/System.out java/io/PrintStream
		sipush 10
		sipush 4
		sipush 2
		imul
		isub
		invokevirtual java/io/PrintStream.print(I)V
		getstatic java/lang/System.out java/io/PrintStream
		invokevirtual java/io/PrintStream.println()V
		getstatic java/lang/System.out java/io/PrintStream
		ldc "Resultado esperado eh 12: "
		invokevirtual java/io/PrintStream.print(java/lang/String)V
		getstatic java/lang/System.out java/io/PrintStream
		sipush 10
		sipush 4
		isub
		sipush 2
		imul
		invokevirtual java/io/PrintStream.print(I)V
		getstatic java/lang/System.out java/io/PrintStream
		invokevirtual java/io/PrintStream.println()V
		getstatic java/lang/System.out java/io/PrintStream
		ldc "Resultado esperado eh 9: "
		invokevirtual java/io/PrintStream.print(java/lang/String)V
		getstatic java/lang/System.out java/io/PrintStream
		sipush 10
		sipush 2
		idiv
		sipush 2
		imul
		sipush 1
		isub
		invokevirtual java/io/PrintStream.print(I)V
		getstatic java/lang/System.out java/io/PrintStream
		invokevirtual java/io/PrintStream.println()V
		getstatic java/lang/System.out java/io/PrintStream
		ldc "Resultado esperado eh 9: "
		invokevirtual java/io/PrintStream.print(java/lang/String)V
		getstatic java/lang/System.out java/io/PrintStream
		sipush 10
		sipush 2
		idiv
		sipush 2
		imul
		sipush 1
		isub
		invokevirtual java/io/PrintStream.print(I)V
		getstatic java/lang/System.out java/io/PrintStream
		invokevirtual java/io/PrintStream.println()V
		return
	}
}
